{
  "fetchedAt": "2026-03-09T18:30:40.409Z",
  "timezone": "Pacific/Auckland",
  "trigger": {
    "type": "outages",
    "previousSha256": "6088a224bb082b937461ce28e005e0e0e27ee3b9cf9b8aaab6e63e4dd1bcf6e9",
    "newSha256": "c80e4ce28a6f254917dc1336c08272e5e2fba696d36f95d2c66367fecf4c8e05"
  },
  "sources": {
    "outages": "https://outages.topenergy.co.nz/api/outages",
    "regions": "https://outages.topenergy.co.nz/api/outages/regions",
    "kmzPlanned": "https://outages.topenergy.co.nz/storage/kmz/polygonsPlannedAll.kmz",
    "kmzActive": "https://outages.topenergy.co.nz/storage/kmz/polygonsActiveAll.kmz",
    "kmzAll": "https://outages.topenergy.co.nz/storage/kmz/polygonsAll.kmz",
    "mapUrl": "https://outages.topenergy.co.nz/"
  },
  "archiveBase": "topenergy/archive/2026-03-10/20260310_073040",
  "screenshot": {
    "attempted": true,
    "captured": true,
    "currentPath": "topenergy/current/mapScreenshot.png"
  },
  "outageInfo": {
    "enabled": true,
    "currentDir": "topenergy/current/outages",
    "archiveDir": "topenergy/archive/2026-03-10/20260310_073040/outages",
    "endpointTemplate": "https://outages.topenergy.co.nz/api/outage/{id}/info",
    "totalIds": 18,
    "failedIds": []
  },
  "files": [
    {
      "key": "outages",
      "currentPath": "topenergy/current/outages.json",
      "sha256": "c80e4ce28a6f254917dc1336c08272e5e2fba696d36f95d2c66367fecf4c8e05",
      "sourceUrl": "https://outages.topenergy.co.nz/api/outages",
      "byteLength": 1855
    },
    {
      "key": "regions",
      "currentPath": "topenergy/current/regions.json",
      "sha256": "9ff7db3138f31ef01aaf0b196875ac72c70687b76c97d4c902482d498483ef24",
      "sourceUrl": "https://outages.topenergy.co.nz/api/outages/regions",
      "byteLength": 7824
    },
    {
      "key": "polygonsPlannedAll",
      "currentPath": "topenergy/current/polygonsPlannedAll.kmz",
      "sha256": "137136760af2a7405d35f5cf5c0a1cccacb3a121011f2098fec8818a59f491db",
      "sourceUrl": "https://outages.topenergy.co.nz/storage/kmz/polygonsPlannedAll.kmz",
      "byteLength": 21140
    },
    {
      "key": "polygonsActiveAll",
      "currentPath": "topenergy/current/polygonsActiveAll.kmz",
      "sha256": "a7d2bd6682cbcd87c62def460ed64dbc28e9d951254f100e34a275abf1926a9b",
      "sourceUrl": "https://outages.topenergy.co.nz/storage/kmz/polygonsActiveAll.kmz",
      "byteLength": 351
    },
    {
      "key": "polygonsAll",
      "currentPath": "topenergy/current/polygonsAll.kmz",
      "sha256": "b2112ba0892b7adc2dae0d1bf256caf4e8e9e47f46ea7e1180305c36ad3f46df",
      "sourceUrl": "https://outages.topenergy.co.nz/storage/kmz/polygonsAll.kmz",
      "byteLength": 21139
    },
    {
      "key": "mapScreenshot",
      "currentPath": "topenergy/current/mapScreenshot.png",
      "sha256": "fa86b16e653a6b457abcb18757d9f6ea1df54568377b105705b0429588bedc35",
      "sourceUrl": "https://outages.topenergy.co.nz/",
      "byteLength": 398684
    }
  ]
}
