{
  "additionalInformation": "",
  "alternativeEstimatedRestorationDate": "",
  "alternativeEstimatedRestorationTime": "",
  "alternativeStartDate": "",
  "alternativeStartTime": "",
  "cause": "Vandalism",
  "customersAffected": "26",
  "duration": "Unknown",
  "estimatedRestorationDate": "18/05/2026",
  "estimatedRestorationTime": "04:30 PM",
  "feeder": "TOWAI",
  "lastUpdateTime": "18/05/2026 02:34 PM",
  "noticeType": "Unplanned",
  "offsupply": "1",
  "startDate": "18/05/2026",
  "startTime": "02:32 PM",
  "status": "Active",
  "streets": {
    "hiddenStreets": "",
    "showStreets": "NELSON ROAD, TAHIWI ROAD, TAPUHI ROAD, WAIOTU ROAD"
  },
  "suburbs": "HIKURANGI, HUKERENUI"
}
