{
  "additionalInformation": "",
  "alternativeEstimatedRestorationDate": "01/06/2026",
  "alternativeEstimatedRestorationTime": "03:00 PM",
  "alternativeStartDate": "01/06/2026",
  "alternativeStartTime": "10:00 AM",
  "cause": "Line Maintenance",
  "customersAffected": "27",
  "duration": "Unknown",
  "estimatedRestorationDate": "25/05/2026",
  "estimatedRestorationTime": "03:00 PM",
  "feeder": "RIVERVIEW",
  "lastUpdateTime": "21/04/2026 09:45 AM",
  "noticeType": "Planned",
  "offsupply": "0",
  "startDate": "25/05/2026",
  "startTime": "10:00 AM",
  "status": "Active",
  "streets": {
    "hiddenStreets": "",
    "showStreets": "SKUDDERS BEACH ROAD, TITOKI PLACE"
  },
  "suburbs": "KERIKERI"
}
