{
  "fetchedAt": "2026-02-11T20:56:40.890Z",
  "timezone": "Pacific/Auckland",
  "trigger": {
    "type": "outages",
    "previousSha256": "4bbb0ca9f5dabc0430968139eb9b3590eceec878cf3124d133573f2357797b53",
    "newSha256": "4e91ae887c4c038b3f8e7977495468c466c5482b6b7ee6415c323f84d6fee5f5"
  },
  "sources": {
    "outages": "https://outages.topenergy.co.nz/api/outages",
    "regions": "https://outages.topenergy.co.nz/api/outages/regions",
    "kmzPlanned": "https://outages.topenergy.co.nz/storage/kmz/polygonsPlannedAll.kmz",
    "kmzActive": "https://outages.topenergy.co.nz/storage/kmz/polygonsActiveAll.kmz",
    "kmzAll": "https://outages.topenergy.co.nz/storage/kmz/polygonsAll.kmz",
    "mapUrl": "https://outages.topenergy.co.nz/"
  },
  "archiveBase": "topenergy/archive/2026-02-12/20260212_095640",
  "screenshot": {
    "attempted": true,
    "captured": true,
    "currentPath": "topenergy/current/mapScreenshot.png"
  },
  "outageInfo": {
    "enabled": true,
    "currentDir": "topenergy/current/outages",
    "archiveDir": "topenergy/archive/2026-02-12/20260212_095640/outages",
    "endpointTemplate": "https://outages.topenergy.co.nz/api/outage/{id}/info",
    "totalIds": 15,
    "failedIds": []
  },
  "files": [
    {
      "key": "outages",
      "currentPath": "topenergy/current/outages.json",
      "sha256": "4e91ae887c4c038b3f8e7977495468c466c5482b6b7ee6415c323f84d6fee5f5",
      "sourceUrl": "https://outages.topenergy.co.nz/api/outages",
      "byteLength": 1559
    },
    {
      "key": "regions",
      "currentPath": "topenergy/current/regions.json",
      "sha256": "3b4dca5fc6dfaaf290501b745fc4ff0d3ad3fd9367c0d9e3a3dc5428e56f8e83",
      "sourceUrl": "https://outages.topenergy.co.nz/api/outages/regions",
      "byteLength": 6618
    },
    {
      "key": "polygonsPlannedAll",
      "currentPath": "topenergy/current/polygonsPlannedAll.kmz",
      "sha256": "520b69fb2fc04566e3fa7b0c9e1f591498e104065ac1261e7db49c04f3cf4528",
      "sourceUrl": "https://outages.topenergy.co.nz/storage/kmz/polygonsPlannedAll.kmz",
      "byteLength": 16300
    },
    {
      "key": "polygonsActiveAll",
      "currentPath": "topenergy/current/polygonsActiveAll.kmz",
      "sha256": "d68102239e6a61cfeae78cea99bcd0854ee826a9499051402019ad9fb9df982d",
      "sourceUrl": "https://outages.topenergy.co.nz/storage/kmz/polygonsActiveAll.kmz",
      "byteLength": 1542
    },
    {
      "key": "polygonsAll",
      "currentPath": "topenergy/current/polygonsAll.kmz",
      "sha256": "4caa3f321a874feede3da1a67ae8f67c9930b3c87297f6b42ff3d9c08e44f5a0",
      "sourceUrl": "https://outages.topenergy.co.nz/storage/kmz/polygonsAll.kmz",
      "byteLength": 17338
    },
    {
      "key": "mapScreenshot",
      "currentPath": "topenergy/current/mapScreenshot.png",
      "sha256": "2c80eaf3bf419c851d8864abcc8d8782620b7f21e2c65aece5b17b7ca2c62fa1",
      "sourceUrl": "https://outages.topenergy.co.nz/",
      "byteLength": 411090
    }
  ]
}
