{
  "additionalInformation": "",
  "alternativeEstimatedRestorationDate": "08/05/2026",
  "alternativeEstimatedRestorationTime": "02:00 PM",
  "alternativeStartDate": "08/05/2026",
  "alternativeStartTime": "09:00 AM",
  "cause": "Line Maintenance",
  "customersAffected": "43",
  "duration": "Unknown",
  "estimatedRestorationDate": "06/05/2026",
  "estimatedRestorationTime": "02:00 PM",
  "feeder": "Sub-Transmission",
  "lastUpdateTime": "04/04/2026 12:56 PM",
  "noticeType": "Planned",
  "offsupply": "0",
  "startDate": "06/05/2026",
  "startTime": "09:00 AM",
  "status": "Active",
  "streets": {
    "hiddenStreets": "WHANGAROA ROAD, WHITE ROAD",
    "showStreets": "DIP ROAD, LEACOCK ROAD, OMAUNU ROAD, STATE HIGHWAY 10, WAIKOURA ROAD"
  },
  "suburbs": "KAEO"
}
