{
  "fetchedAt": "2026-05-26T20:15:25.389Z",
  "timezone": "Pacific/Auckland",
  "trigger": {
    "type": "outages",
    "previousSha256": "8d68b11e5622f74b2b8bd13a1cb2a2b1349ba328b6ac8a54c71b4c4f30aa71c4",
    "newSha256": "ac856a48c688c0285757463266e28899ec2d51976dc61e7d67e52ce1841030cd"
  },
  "sources": {
    "outages": "https://outages.topenergy.co.nz/api/outages",
    "regions": "https://outages.topenergy.co.nz/api/outages/regions",
    "kmzPlanned": "https://outages.topenergy.co.nz/storage/kmz/polygonsPlannedAll.kmz",
    "kmzActive": "https://outages.topenergy.co.nz/storage/kmz/polygonsActiveAll.kmz",
    "kmzAll": "https://outages.topenergy.co.nz/storage/kmz/polygonsAll.kmz",
    "mapUrl": "https://outages.topenergy.co.nz/"
  },
  "archiveBase": "topenergy/archive/2026-05-27/20260527_081525",
  "screenshot": {
    "attempted": false,
    "captured": false,
    "currentPath": "topenergy/current/mapScreenshot.png"
  },
  "outageInfo": {
    "enabled": true,
    "currentDir": "topenergy/current/outages",
    "archiveDir": "topenergy/archive/2026-05-27/20260527_081525/outages",
    "endpointTemplate": "https://outages.topenergy.co.nz/api/outage/{id}/info",
    "totalIds": 18,
    "failedIds": []
  },
  "files": [
    {
      "key": "outages",
      "currentPath": "topenergy/current/outages.json",
      "sha256": "ac856a48c688c0285757463266e28899ec2d51976dc61e7d67e52ce1841030cd",
      "sourceUrl": "https://outages.topenergy.co.nz/api/outages",
      "byteLength": 1858
    },
    {
      "key": "regions",
      "currentPath": "topenergy/current/regions.json",
      "sha256": "89cf2f60ce27b4e4aaef2116fdda93e9f7e4b6d742229f83b864f67010796f61",
      "sourceUrl": "https://outages.topenergy.co.nz/api/outages/regions",
      "byteLength": 7715
    },
    {
      "key": "polygonsPlannedAll",
      "currentPath": "topenergy/current/polygonsPlannedAll.kmz",
      "sha256": "5a7dcc5f53e01105bf184b12f0bbcda4d946da769d9dde8e09c6932ca50a1cfd",
      "sourceUrl": "https://outages.topenergy.co.nz/storage/kmz/polygonsPlannedAll.kmz",
      "byteLength": 20428
    },
    {
      "key": "polygonsActiveAll",
      "currentPath": "topenergy/current/polygonsActiveAll.kmz",
      "sha256": "3f779ec52f17faba06a28636f8e502d195736f2e1bc256d1b41142818c856655",
      "sourceUrl": "https://outages.topenergy.co.nz/storage/kmz/polygonsActiveAll.kmz",
      "byteLength": 351
    },
    {
      "key": "polygonsAll",
      "currentPath": "topenergy/current/polygonsAll.kmz",
      "sha256": "230aa51b87b6bbfb1f1c65d786d1ed24ab6e32555bfeb9c0ca523a3fa3b60144",
      "sourceUrl": "https://outages.topenergy.co.nz/storage/kmz/polygonsAll.kmz",
      "byteLength": 20354
    }
  ]
}
