{
  "fetchedAt": "2026-02-14T03:33:40.099Z",
  "timezone": "Pacific/Auckland",
  "trigger": {
    "type": "outages",
    "previousSha256": "14b50771974a743020dd398570c96157e6bfdd24084ec9787db72e9f0524f9c3",
    "newSha256": "e8414bff38f42639484628df47c2c798a99157280ab430cbfc32056ec4fa1fbe"
  },
  "sources": {
    "outages": "https://outages.topenergy.co.nz/api/outages",
    "regions": "https://outages.topenergy.co.nz/api/outages/regions",
    "kmzPlanned": "https://outages.topenergy.co.nz/storage/kmz/polygonsPlannedAll.kmz",
    "kmzActive": "https://outages.topenergy.co.nz/storage/kmz/polygonsActiveAll.kmz",
    "kmzAll": "https://outages.topenergy.co.nz/storage/kmz/polygonsAll.kmz",
    "mapUrl": "https://outages.topenergy.co.nz/"
  },
  "archiveBase": "topenergy/archive/2026-02-14/20260214_163340",
  "screenshot": {
    "attempted": true,
    "captured": true,
    "currentPath": "topenergy/current/mapScreenshot.png"
  },
  "outageInfo": {
    "enabled": true,
    "currentDir": "topenergy/current/outages",
    "archiveDir": "topenergy/archive/2026-02-14/20260214_163340/outages",
    "endpointTemplate": "https://outages.topenergy.co.nz/api/outage/{id}/info",
    "totalIds": 18,
    "failedIds": []
  },
  "files": [
    {
      "key": "outages",
      "currentPath": "topenergy/current/outages.json",
      "sha256": "e8414bff38f42639484628df47c2c798a99157280ab430cbfc32056ec4fa1fbe",
      "sourceUrl": "https://outages.topenergy.co.nz/api/outages",
      "byteLength": 1857
    },
    {
      "key": "regions",
      "currentPath": "topenergy/current/regions.json",
      "sha256": "e6d97535cf8fd32e313bc84ea0dd8cf47a2dae8d06a5115245d4162a0d9c2cb5",
      "sourceUrl": "https://outages.topenergy.co.nz/api/outages/regions",
      "byteLength": 7954
    },
    {
      "key": "polygonsPlannedAll",
      "currentPath": "topenergy/current/polygonsPlannedAll.kmz",
      "sha256": "f00811938f08f87bec6f1897617bf83992f79a2461948b29e0432082e0e8dae1",
      "sourceUrl": "https://outages.topenergy.co.nz/storage/kmz/polygonsPlannedAll.kmz",
      "byteLength": 19670
    },
    {
      "key": "polygonsActiveAll",
      "currentPath": "topenergy/current/polygonsActiveAll.kmz",
      "sha256": "9cb954bedc752b1ecf08488b45afe863d0eb615fa7425abc3333e818780f5ed7",
      "sourceUrl": "https://outages.topenergy.co.nz/storage/kmz/polygonsActiveAll.kmz",
      "byteLength": 1556
    },
    {
      "key": "polygonsAll",
      "currentPath": "topenergy/current/polygonsAll.kmz",
      "sha256": "73ee46bff5b3d191e9972138814dd19e3ddfa967f7dd9ad89fb8b2cac4e24fb9",
      "sourceUrl": "https://outages.topenergy.co.nz/storage/kmz/polygonsAll.kmz",
      "byteLength": 20670
    },
    {
      "key": "mapScreenshot",
      "currentPath": "topenergy/current/mapScreenshot.png",
      "sha256": "6e5a90acb31a07ad2014441a8452c3c53428157d1c7b2a87653dce1714a7fbac",
      "sourceUrl": "https://outages.topenergy.co.nz/",
      "byteLength": 411590
    }
  ]
}
