{
  "fetchedAt": "2026-03-06T20:48:40.616Z",
  "timezone": "Pacific/Auckland",
  "trigger": {
    "type": "outages",
    "previousSha256": "733628dc77d6089273db8b86684215d78548b3212eb9af8bff72909e68b464d1",
    "newSha256": "2b43adafc9a61da3780d66b05ef81aab770c472ac68f7391da57f88e4da41d2f"
  },
  "sources": {
    "outages": "https://outages.topenergy.co.nz/api/outages",
    "regions": "https://outages.topenergy.co.nz/api/outages/regions",
    "kmzPlanned": "https://outages.topenergy.co.nz/storage/kmz/polygonsPlannedAll.kmz",
    "kmzActive": "https://outages.topenergy.co.nz/storage/kmz/polygonsActiveAll.kmz",
    "kmzAll": "https://outages.topenergy.co.nz/storage/kmz/polygonsAll.kmz",
    "mapUrl": "https://outages.topenergy.co.nz/"
  },
  "archiveBase": "topenergy/archive/2026-03-07/20260307_094840",
  "screenshot": {
    "attempted": true,
    "captured": true,
    "currentPath": "topenergy/current/mapScreenshot.png"
  },
  "outageInfo": {
    "enabled": true,
    "currentDir": "topenergy/current/outages",
    "archiveDir": "topenergy/archive/2026-03-07/20260307_094840/outages",
    "endpointTemplate": "https://outages.topenergy.co.nz/api/outage/{id}/info",
    "totalIds": 15,
    "failedIds": []
  },
  "files": [
    {
      "key": "outages",
      "currentPath": "topenergy/current/outages.json",
      "sha256": "2b43adafc9a61da3780d66b05ef81aab770c472ac68f7391da57f88e4da41d2f",
      "sourceUrl": "https://outages.topenergy.co.nz/api/outages",
      "byteLength": 1556
    },
    {
      "key": "regions",
      "currentPath": "topenergy/current/regions.json",
      "sha256": "e357ea5398d7a51a58d260ce313d1c6107df07b56937b87838cd095a78b0923b",
      "sourceUrl": "https://outages.topenergy.co.nz/api/outages/regions",
      "byteLength": 6539
    },
    {
      "key": "polygonsPlannedAll",
      "currentPath": "topenergy/current/polygonsPlannedAll.kmz",
      "sha256": "49c9c962cdb0f8aef559e65233ff753d455fd83e32c35b6b00c296afd9631006",
      "sourceUrl": "https://outages.topenergy.co.nz/storage/kmz/polygonsPlannedAll.kmz",
      "byteLength": 16767
    },
    {
      "key": "polygonsActiveAll",
      "currentPath": "topenergy/current/polygonsActiveAll.kmz",
      "sha256": "b4c60ca019e85917af9e111922860728982b746d2169bde3b30fdf1d19592f6d",
      "sourceUrl": "https://outages.topenergy.co.nz/storage/kmz/polygonsActiveAll.kmz",
      "byteLength": 351
    },
    {
      "key": "polygonsAll",
      "currentPath": "topenergy/current/polygonsAll.kmz",
      "sha256": "0ce799a3f42419d04c6a38aba9306f2b017c03b0af58c4f2bca3abd057ae5bdc",
      "sourceUrl": "https://outages.topenergy.co.nz/storage/kmz/polygonsAll.kmz",
      "byteLength": 16730
    },
    {
      "key": "mapScreenshot",
      "currentPath": "topenergy/current/mapScreenshot.png",
      "sha256": "fa86b16e653a6b457abcb18757d9f6ea1df54568377b105705b0429588bedc35",
      "sourceUrl": "https://outages.topenergy.co.nz/",
      "byteLength": 398684
    }
  ]
}
