{
  "fetchedAt": "2026-05-28T18:47:24.890Z",
  "timezone": "Pacific/Auckland",
  "trigger": {
    "type": "outages",
    "previousSha256": "006573000dfe85311980aa4aafc3624e3a587de5a92cd5933ed63ad75088651b",
    "newSha256": "80ec85754e25b87c7a351f57d8fb94e4687496277e0fce49e87c640e03f50598"
  },
  "sources": {
    "outages": "https://outages.topenergy.co.nz/api/outages",
    "regions": "https://outages.topenergy.co.nz/api/outages/regions",
    "kmzPlanned": "https://outages.topenergy.co.nz/storage/kmz/polygonsPlannedAll.kmz",
    "kmzActive": "https://outages.topenergy.co.nz/storage/kmz/polygonsActiveAll.kmz",
    "kmzAll": "https://outages.topenergy.co.nz/storage/kmz/polygonsAll.kmz",
    "mapUrl": "https://outages.topenergy.co.nz/"
  },
  "archiveBase": "topenergy/archive/2026-05-29/20260529_064724",
  "screenshot": {
    "attempted": false,
    "captured": false,
    "currentPath": "topenergy/current/mapScreenshot.png"
  },
  "outageInfo": {
    "enabled": true,
    "currentDir": "topenergy/current/outages",
    "archiveDir": "topenergy/archive/2026-05-29/20260529_064724/outages",
    "endpointTemplate": "https://outages.topenergy.co.nz/api/outage/{id}/info",
    "totalIds": 14,
    "failedIds": []
  },
  "files": [
    {
      "key": "outages",
      "currentPath": "topenergy/current/outages.json",
      "sha256": "80ec85754e25b87c7a351f57d8fb94e4687496277e0fce49e87c640e03f50598",
      "sourceUrl": "https://outages.topenergy.co.nz/api/outages",
      "byteLength": 1454
    },
    {
      "key": "regions",
      "currentPath": "topenergy/current/regions.json",
      "sha256": "ef3936383dd2d536da569da0e7015aa9ab93614dc7fb18c7c7fac3518581cbbf",
      "sourceUrl": "https://outages.topenergy.co.nz/api/outages/regions",
      "byteLength": 5989
    },
    {
      "key": "polygonsPlannedAll",
      "currentPath": "topenergy/current/polygonsPlannedAll.kmz",
      "sha256": "b07a6763f7ea5bf50fb665c3d39005550059148665f7e8bf8278b39588e101ad",
      "sourceUrl": "https://outages.topenergy.co.nz/storage/kmz/polygonsPlannedAll.kmz",
      "byteLength": 14878
    },
    {
      "key": "polygonsActiveAll",
      "currentPath": "topenergy/current/polygonsActiveAll.kmz",
      "sha256": "50a3c2f45acd8f8f0090f7db317340e4ec50c9e0060c83efeb2041ae0859d8dc",
      "sourceUrl": "https://outages.topenergy.co.nz/storage/kmz/polygonsActiveAll.kmz",
      "byteLength": 1557
    },
    {
      "key": "polygonsAll",
      "currentPath": "topenergy/current/polygonsAll.kmz",
      "sha256": "72232e02d38f54228433f4cbce98495d0757f856b495adc86fb17a1d55b27796",
      "sourceUrl": "https://outages.topenergy.co.nz/storage/kmz/polygonsAll.kmz",
      "byteLength": 16996
    }
  ]
}
