{
  "additionalInformation": "",
  "alternativeEstimatedRestorationDate": "",
  "alternativeEstimatedRestorationTime": "",
  "alternativeStartDate": "",
  "alternativeStartTime": "",
  "cause": "Under Investigation",
  "customersAffected": "1",
  "duration": "Unknown",
  "estimatedRestorationDate": null,
  "estimatedRestorationTime": null,
  "feeder": "HOREKE",
  "lastUpdateTime": "30/01/2026 07:51 AM",
  "noticeType": "Unplanned",
  "offsupply": "1",
  "startDate": "30/01/2026",
  "startTime": "07:51 AM",
  "status": "Active",
  "streets": {
    "hiddenStreets": "",
    "showStreets": "IMMS ROAD"
  },
  "suburbs": "OKAIHAU"
}
