{
  "additionalInformation": "",
  "alternativeEstimatedRestorationDate": "",
  "alternativeEstimatedRestorationTime": "",
  "alternativeStartDate": "",
  "alternativeStartTime": "",
  "cause": "Equipment fault",
  "customersAffected": "2",
  "duration": "Unknown",
  "estimatedRestorationDate": "14/02/2026",
  "estimatedRestorationTime": "11:30 AM",
  "feeder": "BROADWOOD",
  "lastUpdateTime": "13/02/2026 08:57 PM",
  "noticeType": "Unplanned",
  "offsupply": "1",
  "startDate": "13/02/2026",
  "startTime": "08:56 PM",
  "status": "Active",
  "streets": {
    "hiddenStreets": "",
    "showStreets": "TAKAHUE ROAD"
  },
  "suburbs": "KAITAIA"
}
