{
  "archiveFilename": "latest_2025-08-18T21-51-52-062Z.xml",
  "folderPath": "alerts/archive/2025/08/latest_2025-08-18T21-51-52-062Z",
  "processedAt": "2026-01-18T08:53:00.620Z",
  "entryCount": 5,
  "written": [
    {
      "id": "2.49.0.0.554.0.severeweather.nz.20250818211628730.0",
      "capUrl": "https://alerts.metservice.com/cap/alert?id=2.49.0.0.554.0.severeweather.nz.20250818211628730.0",
      "file": "2.49.0.0.554.0.severeweather.nz.20250818211628730.0.xml"
    }
  ],
  "skipped": [
    {
      "id": "2.49.0.0.554.0.roadsnow.arthurspass.20250818093958876.0",
      "reason": "already_exists"
    },
    {
      "id": "2.49.0.0.554.0.roadsnow.desertroad.20250818093958897.0",
      "reason": "already_exists"
    },
    {
      "id": "2.49.0.0.554.0.roadsnow.lewispass.20250818093958874.0",
      "reason": "already_exists"
    },
    {
      "id": "2.49.0.0.554.0.roadsnow.porterspass.20250818093958875.0",
      "reason": "already_exists"
    }
  ],
  "failed": [],
  "archivePath": "alerts/archive/2025/08/latest_2025-08-18T21-51-52-062Z.xml",
  "updatedAt": "2026-01-26T03:14:36.510Z"
}