{
  "fetchedAt": "2026-01-18T23:51:40.415Z",
  "timezone": "Pacific/Auckland",
  "trigger": {
    "type": "outages",
    "previousSha256": "e21a7e9c24d855cce65d8bca08a13bbfe2475ea27d65b92bb1e123e40d171e35",
    "newSha256": "1a036bd0f6d675469c262058249d3e389d7e502d07835d6705d93cc7bdd0b506"
  },
  "sources": {
    "outages": "https://outages.topenergy.co.nz/api/outages",
    "regions": "https://outages.topenergy.co.nz/api/outages/regions",
    "kmzPlanned": "https://outages.topenergy.co.nz/storage/kmz/polygonsPlannedAll.kmz",
    "kmzActive": "https://outages.topenergy.co.nz/storage/kmz/polygonsActiveAll.kmz",
    "kmzAll": "https://outages.topenergy.co.nz/storage/kmz/polygonsAll.kmz",
    "mapUrl": "https://outages.topenergy.co.nz/"
  },
  "archiveBase": "topenergy/archive/2026-01-19/20260119_125140",
  "screenshot": {
    "attempted": true,
    "captured": true,
    "currentPath": "topenergy/current/mapScreenshot.png"
  },
  "outageInfo": {
    "enabled": true,
    "currentDir": "topenergy/current/outages",
    "archiveDir": "topenergy/archive/2026-01-19/20260119_125140/outages",
    "endpointTemplate": "https://outages.topenergy.co.nz/api/outage/{id}/info",
    "totalIds": 17,
    "failedIds": []
  },
  "files": [
    {
      "key": "outages",
      "currentPath": "topenergy/current/outages.json",
      "sha256": "1a036bd0f6d675469c262058249d3e389d7e502d07835d6705d93cc7bdd0b506",
      "sourceUrl": "https://outages.topenergy.co.nz/api/outages",
      "byteLength": 1758
    },
    {
      "key": "regions",
      "currentPath": "topenergy/current/regions.json",
      "sha256": "b89e2a5ed3f8a9dd78af96d0f1da93dd38589fbdf486ca80baa09e6fd2d1efc8",
      "sourceUrl": "https://outages.topenergy.co.nz/api/outages/regions",
      "byteLength": 7454
    },
    {
      "key": "polygonsPlannedAll",
      "currentPath": "topenergy/current/polygonsPlannedAll.kmz",
      "sha256": "6190ad44bcd03bab999d9869069ad4d80ebfdba080ddcb87e86c46431d8151ba",
      "sourceUrl": "https://outages.topenergy.co.nz/storage/kmz/polygonsPlannedAll.kmz",
      "byteLength": 17545
    },
    {
      "key": "polygonsActiveAll",
      "currentPath": "topenergy/current/polygonsActiveAll.kmz",
      "sha256": "2f5ecd659d21d74897af4230346bb2767776430149bd6e53e74b2128a38071a6",
      "sourceUrl": "https://outages.topenergy.co.nz/storage/kmz/polygonsActiveAll.kmz",
      "byteLength": 2824
    },
    {
      "key": "polygonsAll",
      "currentPath": "topenergy/current/polygonsAll.kmz",
      "sha256": "272fca3cd86b81886043abc20535cf958aa58c7003d26c4ac0ae388644f9d994",
      "sourceUrl": "https://outages.topenergy.co.nz/storage/kmz/polygonsAll.kmz",
      "byteLength": 18736
    },
    {
      "key": "mapScreenshot",
      "currentPath": "topenergy/current/mapScreenshot.png",
      "sha256": "46234cab5817eab06c9fbd073d2372b9baef9797df7e47b5c8ffe51550dd8cd9",
      "sourceUrl": "https://outages.topenergy.co.nz/",
      "byteLength": 405363
    }
  ]
}
