{
  "fetchedAt": "2025-12-29T07:22:20.168Z",
  "timezone": "Pacific/Auckland",
  "trigger": {
    "type": "outages",
    "previousSha256": "38cf8a7a56fbaa8e69e9467b7d60abee9882465649deedd9dac1dfbfd50d9d81",
    "newSha256": "8095346b97412098ce958155ded31af8e1f49a99b0f103e1b742e9d70dff8e12"
  },
  "sources": {
    "outages": "https://outages.topenergy.co.nz/api/outages",
    "regions": "https://outages.topenergy.co.nz/api/outages/regions",
    "kmzPlanned": "https://outages.topenergy.co.nz/storage/kmz/polygonsPlannedAll.kmz",
    "kmzActive": "https://outages.topenergy.co.nz/storage/kmz/polygonsActiveAll.kmz",
    "kmzAll": "https://outages.topenergy.co.nz/storage/kmz/polygonsAll.kmz",
    "mapUrl": "https://outages.topenergy.co.nz/"
  },
  "archiveBase": "topenergy/archive/2025-12-29/20251229_202220",
  "screenshot": {
    "attempted": true,
    "captured": true,
    "currentPath": "topenergy/current/mapScreenshot.png"
  },
  "files": [
    {
      "key": "outages",
      "currentPath": "topenergy/current/outages.json",
      "sha256": "8095346b97412098ce958155ded31af8e1f49a99b0f103e1b742e9d70dff8e12",
      "sourceUrl": "https://outages.topenergy.co.nz/api/outages",
      "byteLength": 563
    },
    {
      "key": "regions",
      "currentPath": "topenergy/current/regions.json",
      "sha256": "fc74e8f800442df64b0e23bfd5d7ff6247f3f94dda68651ebcd9a755eb6fe7d9",
      "sourceUrl": "https://outages.topenergy.co.nz/api/outages/regions",
      "byteLength": 2241
    },
    {
      "key": "polygonsPlannedAll",
      "currentPath": "topenergy/current/polygonsPlannedAll.kmz",
      "sha256": "5f662f38484df00f402a8611f293918df4f18494ac8be658cf94033fb7d9e088",
      "sourceUrl": "https://outages.topenergy.co.nz/storage/kmz/polygonsPlannedAll.kmz",
      "byteLength": 6432
    },
    {
      "key": "polygonsActiveAll",
      "currentPath": "topenergy/current/polygonsActiveAll.kmz",
      "sha256": "5746d3922266a8824464476c88f0b1186938a88b82e849678a6958c19cbc33d1",
      "sourceUrl": "https://outages.topenergy.co.nz/storage/kmz/polygonsActiveAll.kmz",
      "byteLength": 351
    },
    {
      "key": "polygonsAll",
      "currentPath": "topenergy/current/polygonsAll.kmz",
      "sha256": "7352443303aa90b0dd23a57c8c2a6508de8743b248c7c57fea47e3b545339f41",
      "sourceUrl": "https://outages.topenergy.co.nz/storage/kmz/polygonsAll.kmz",
      "byteLength": 6405
    },
    {
      "key": "mapScreenshot",
      "currentPath": "topenergy/current/mapScreenshot.png",
      "sha256": "3bd4c4e6aca3d1ae9e2981c3bd1d3bfaa8c2a5e4681a758c4c452f790d3222f9",
      "sourceUrl": "https://outages.topenergy.co.nz/",
      "byteLength": 398865
    }
  ]
}
