{
  "fetchedAt": "2026-03-08T21:02:40.308Z",
  "timezone": "Pacific/Auckland",
  "trigger": {
    "type": "outages",
    "previousSha256": "506eb790812bebb5642530304746df30e87dbc9a076db1887c230745ba6a8701",
    "newSha256": "afe6696ffc0f998b55fdc8c624549ccf2884b1c25e390fc55f2db21f02cf2eae"
  },
  "sources": {
    "outages": "https://outages.topenergy.co.nz/api/outages",
    "regions": "https://outages.topenergy.co.nz/api/outages/regions",
    "kmzPlanned": "https://outages.topenergy.co.nz/storage/kmz/polygonsPlannedAll.kmz",
    "kmzActive": "https://outages.topenergy.co.nz/storage/kmz/polygonsActiveAll.kmz",
    "kmzAll": "https://outages.topenergy.co.nz/storage/kmz/polygonsAll.kmz",
    "mapUrl": "https://outages.topenergy.co.nz/"
  },
  "archiveBase": "topenergy/archive/2026-03-09/20260309_100240",
  "screenshot": {
    "attempted": true,
    "captured": true,
    "currentPath": "topenergy/current/mapScreenshot.png"
  },
  "outageInfo": {
    "enabled": true,
    "currentDir": "topenergy/current/outages",
    "archiveDir": "topenergy/archive/2026-03-09/20260309_100240/outages",
    "endpointTemplate": "https://outages.topenergy.co.nz/api/outage/{id}/info",
    "totalIds": 17,
    "failedIds": []
  },
  "files": [
    {
      "key": "outages",
      "currentPath": "topenergy/current/outages.json",
      "sha256": "afe6696ffc0f998b55fdc8c624549ccf2884b1c25e390fc55f2db21f02cf2eae",
      "sourceUrl": "https://outages.topenergy.co.nz/api/outages",
      "byteLength": 1750
    },
    {
      "key": "regions",
      "currentPath": "topenergy/current/regions.json",
      "sha256": "224ecfb4a9b12426a10b57415e1df729f9a5332b8dc3705b50e517e54d76bb04",
      "sourceUrl": "https://outages.topenergy.co.nz/api/outages/regions",
      "byteLength": 7393
    },
    {
      "key": "polygonsPlannedAll",
      "currentPath": "topenergy/current/polygonsPlannedAll.kmz",
      "sha256": "4ac156ca34a2b645a41e800441ecb84f45eb6ed215ae770ec2c6cd57ef3fd2d9",
      "sourceUrl": "https://outages.topenergy.co.nz/storage/kmz/polygonsPlannedAll.kmz",
      "byteLength": 18500
    },
    {
      "key": "polygonsActiveAll",
      "currentPath": "topenergy/current/polygonsActiveAll.kmz",
      "sha256": "bc25152974c2efc6699ef804b78926cd4535b712b9613d757910f6e1caaf7acb",
      "sourceUrl": "https://outages.topenergy.co.nz/storage/kmz/polygonsActiveAll.kmz",
      "byteLength": 351
    },
    {
      "key": "polygonsAll",
      "currentPath": "topenergy/current/polygonsAll.kmz",
      "sha256": "ef768c4add20e29b8421896348774ccf09c94a5fdd767fd72d16d1255b0caedd",
      "sourceUrl": "https://outages.topenergy.co.nz/storage/kmz/polygonsAll.kmz",
      "byteLength": 18526
    },
    {
      "key": "mapScreenshot",
      "currentPath": "topenergy/current/mapScreenshot.png",
      "sha256": "fa86b16e653a6b457abcb18757d9f6ea1df54568377b105705b0429588bedc35",
      "sourceUrl": "https://outages.topenergy.co.nz/",
      "byteLength": 398684
    }
  ]
}
