{
  "fetchedAt": "2026-03-09T20:37:41.426Z",
  "timezone": "Pacific/Auckland",
  "trigger": {
    "type": "outages",
    "previousSha256": "0f9695fef9907f948fca052e30a576decac3bad7fc2b0af634c3a4f1930d9fbb",
    "newSha256": "128f6933c452365e0448bd0d751e9cc4977d7ede40651a649ff4e257fd5a14ee"
  },
  "sources": {
    "outages": "https://outages.topenergy.co.nz/api/outages",
    "regions": "https://outages.topenergy.co.nz/api/outages/regions",
    "kmzPlanned": "https://outages.topenergy.co.nz/storage/kmz/polygonsPlannedAll.kmz",
    "kmzActive": "https://outages.topenergy.co.nz/storage/kmz/polygonsActiveAll.kmz",
    "kmzAll": "https://outages.topenergy.co.nz/storage/kmz/polygonsAll.kmz",
    "mapUrl": "https://outages.topenergy.co.nz/"
  },
  "archiveBase": "topenergy/archive/2026-03-10/20260310_093741",
  "screenshot": {
    "attempted": true,
    "captured": true,
    "currentPath": "topenergy/current/mapScreenshot.png"
  },
  "outageInfo": {
    "enabled": true,
    "currentDir": "topenergy/current/outages",
    "archiveDir": "topenergy/archive/2026-03-10/20260310_093741/outages",
    "endpointTemplate": "https://outages.topenergy.co.nz/api/outage/{id}/info",
    "totalIds": 19,
    "failedIds": []
  },
  "files": [
    {
      "key": "outages",
      "currentPath": "topenergy/current/outages.json",
      "sha256": "128f6933c452365e0448bd0d751e9cc4977d7ede40651a649ff4e257fd5a14ee",
      "sourceUrl": "https://outages.topenergy.co.nz/api/outages",
      "byteLength": 1957
    },
    {
      "key": "regions",
      "currentPath": "topenergy/current/regions.json",
      "sha256": "fdeec4d2d29c2006b2a84d1b01415f319671792640edae5dcc5a337b8609733e",
      "sourceUrl": "https://outages.topenergy.co.nz/api/outages/regions",
      "byteLength": 8251
    },
    {
      "key": "polygonsPlannedAll",
      "currentPath": "topenergy/current/polygonsPlannedAll.kmz",
      "sha256": "fe5dcd2d2effbc55f13ea9be066edb958417eb8a6acd9a5c7361b867d932772b",
      "sourceUrl": "https://outages.topenergy.co.nz/storage/kmz/polygonsPlannedAll.kmz",
      "byteLength": 22225
    },
    {
      "key": "polygonsActiveAll",
      "currentPath": "topenergy/current/polygonsActiveAll.kmz",
      "sha256": "7c3c66f26c8a1421c3a3e8fd0339cf3ac345ba12529bac72fc33738c809be93d",
      "sourceUrl": "https://outages.topenergy.co.nz/storage/kmz/polygonsActiveAll.kmz",
      "byteLength": 1609
    },
    {
      "key": "polygonsAll",
      "currentPath": "topenergy/current/polygonsAll.kmz",
      "sha256": "9604e97d9548dc4c0f3d6077367361ebe525cab3a681976879c4a4a112896613",
      "sourceUrl": "https://outages.topenergy.co.nz/storage/kmz/polygonsAll.kmz",
      "byteLength": 22216
    },
    {
      "key": "mapScreenshot",
      "currentPath": "topenergy/current/mapScreenshot.png",
      "sha256": "b8506bb023e29e01e62e5af63a8d7a58d6f3a95c48517127fdb1cfdaae05dcc3",
      "sourceUrl": "https://outages.topenergy.co.nz/",
      "byteLength": 403034
    }
  ]
}
