{
  "fetchedAt": "2026-03-08T19:37:40.322Z",
  "timezone": "Pacific/Auckland",
  "trigger": {
    "type": "outages",
    "previousSha256": "d9ebd5eca9dd7494640ad2de9a084e706e743df9d61606372fd93f0ec869764a",
    "newSha256": "633ae58d530d24bb2d307632b1009398cecbcda0365988e0ea3fa8554ffc0676"
  },
  "sources": {
    "outages": "https://outages.topenergy.co.nz/api/outages",
    "regions": "https://outages.topenergy.co.nz/api/outages/regions",
    "kmzPlanned": "https://outages.topenergy.co.nz/storage/kmz/polygonsPlannedAll.kmz",
    "kmzActive": "https://outages.topenergy.co.nz/storage/kmz/polygonsActiveAll.kmz",
    "kmzAll": "https://outages.topenergy.co.nz/storage/kmz/polygonsAll.kmz",
    "mapUrl": "https://outages.topenergy.co.nz/"
  },
  "archiveBase": "topenergy/archive/2026-03-09/20260309_083740",
  "screenshot": {
    "attempted": true,
    "captured": true,
    "currentPath": "topenergy/current/mapScreenshot.png"
  },
  "outageInfo": {
    "enabled": true,
    "currentDir": "topenergy/current/outages",
    "archiveDir": "topenergy/archive/2026-03-09/20260309_083740/outages",
    "endpointTemplate": "https://outages.topenergy.co.nz/api/outage/{id}/info",
    "totalIds": 17,
    "failedIds": []
  },
  "files": [
    {
      "key": "outages",
      "currentPath": "topenergy/current/outages.json",
      "sha256": "633ae58d530d24bb2d307632b1009398cecbcda0365988e0ea3fa8554ffc0676",
      "sourceUrl": "https://outages.topenergy.co.nz/api/outages",
      "byteLength": 1750
    },
    {
      "key": "regions",
      "currentPath": "topenergy/current/regions.json",
      "sha256": "224ecfb4a9b12426a10b57415e1df729f9a5332b8dc3705b50e517e54d76bb04",
      "sourceUrl": "https://outages.topenergy.co.nz/api/outages/regions",
      "byteLength": 7393
    },
    {
      "key": "polygonsPlannedAll",
      "currentPath": "topenergy/current/polygonsPlannedAll.kmz",
      "sha256": "eb253ba30cef9e4f62d18fa3f3876de4696cad27f19dffeaf23f676db1bfa3ff",
      "sourceUrl": "https://outages.topenergy.co.nz/storage/kmz/polygonsPlannedAll.kmz",
      "byteLength": 18500
    },
    {
      "key": "polygonsActiveAll",
      "currentPath": "topenergy/current/polygonsActiveAll.kmz",
      "sha256": "d91a65f1c91cd807a332026e5536c961d816069a4cf360d9c60ee9408806dab8",
      "sourceUrl": "https://outages.topenergy.co.nz/storage/kmz/polygonsActiveAll.kmz",
      "byteLength": 351
    },
    {
      "key": "polygonsAll",
      "currentPath": "topenergy/current/polygonsAll.kmz",
      "sha256": "551d7b7fa27f069961aa18ae51a9b1cf550572d025dfc4bdd51f7a4821f407c5",
      "sourceUrl": "https://outages.topenergy.co.nz/storage/kmz/polygonsAll.kmz",
      "byteLength": 18526
    },
    {
      "key": "mapScreenshot",
      "currentPath": "topenergy/current/mapScreenshot.png",
      "sha256": "fa86b16e653a6b457abcb18757d9f6ea1df54568377b105705b0429588bedc35",
      "sourceUrl": "https://outages.topenergy.co.nz/",
      "byteLength": 398684
    }
  ]
}
