{
  "fetchedAt": "2026-03-05T12:18:40.764Z",
  "timezone": "Pacific/Auckland",
  "trigger": {
    "type": "outages",
    "previousSha256": "b071108628393fed221cc9530776b5ee8b36320a71cb620f471135be90142568",
    "newSha256": "b29d8b1ca3d0389ff3594b29bf1152860a5a1730231bf126b64583dd3e7bf19f"
  },
  "sources": {
    "outages": "https://outages.topenergy.co.nz/api/outages",
    "regions": "https://outages.topenergy.co.nz/api/outages/regions",
    "kmzPlanned": "https://outages.topenergy.co.nz/storage/kmz/polygonsPlannedAll.kmz",
    "kmzActive": "https://outages.topenergy.co.nz/storage/kmz/polygonsActiveAll.kmz",
    "kmzAll": "https://outages.topenergy.co.nz/storage/kmz/polygonsAll.kmz",
    "mapUrl": "https://outages.topenergy.co.nz/"
  },
  "archiveBase": "topenergy/archive/2026-03-06/20260306_011840",
  "screenshot": {
    "attempted": true,
    "captured": true,
    "currentPath": "topenergy/current/mapScreenshot.png"
  },
  "outageInfo": {
    "enabled": true,
    "currentDir": "topenergy/current/outages",
    "archiveDir": "topenergy/archive/2026-03-06/20260306_011840/outages",
    "endpointTemplate": "https://outages.topenergy.co.nz/api/outage/{id}/info",
    "totalIds": 16,
    "failedIds": []
  },
  "files": [
    {
      "key": "outages",
      "currentPath": "topenergy/current/outages.json",
      "sha256": "b29d8b1ca3d0389ff3594b29bf1152860a5a1730231bf126b64583dd3e7bf19f",
      "sourceUrl": "https://outages.topenergy.co.nz/api/outages",
      "byteLength": 1659
    },
    {
      "key": "regions",
      "currentPath": "topenergy/current/regions.json",
      "sha256": "67df9b3dfe4e0e87c29c5048dd129490973de0e9183287c67ff707a4c794bb5d",
      "sourceUrl": "https://outages.topenergy.co.nz/api/outages/regions",
      "byteLength": 6981
    },
    {
      "key": "polygonsPlannedAll",
      "currentPath": "topenergy/current/polygonsPlannedAll.kmz",
      "sha256": "f4e036d23b5c06d5d295a707f396b21b2a1c01e7692b3504661d73155eafb524",
      "sourceUrl": "https://outages.topenergy.co.nz/storage/kmz/polygonsPlannedAll.kmz",
      "byteLength": 17851
    },
    {
      "key": "polygonsActiveAll",
      "currentPath": "topenergy/current/polygonsActiveAll.kmz",
      "sha256": "4cc6ef16845de9252cb581a41ef99a72c85e90d5be82fcdffd0a3fe108a3d935",
      "sourceUrl": "https://outages.topenergy.co.nz/storage/kmz/polygonsActiveAll.kmz",
      "byteLength": 351
    },
    {
      "key": "polygonsAll",
      "currentPath": "topenergy/current/polygonsAll.kmz",
      "sha256": "8bcdbd55f8d047fab67f48f52b5de2a015cb66b29f66cea4a0b3b4319c0a1960",
      "sourceUrl": "https://outages.topenergy.co.nz/storage/kmz/polygonsAll.kmz",
      "byteLength": 17819
    },
    {
      "key": "mapScreenshot",
      "currentPath": "topenergy/current/mapScreenshot.png",
      "sha256": "fb25723345df99fea9c50cb090861c4472c8dc26e1c2c2c243d90e9523b38d1b",
      "sourceUrl": "https://outages.topenergy.co.nz/",
      "byteLength": 399142
    }
  ]
}
