{
  "fetchedAt": "2026-05-16T12:01:25.311Z",
  "timezone": "Pacific/Auckland",
  "trigger": {
    "type": "outages",
    "previousSha256": "21980c128e8fb590f11d04b4ab4fc3c2f5b5203df655b7678938783b12fc88c0",
    "newSha256": "474c61e28afb86b2e89bd2640bab58107244275beb44fa84bb4a9d8c6af627b0"
  },
  "sources": {
    "outages": "https://outages.topenergy.co.nz/api/outages",
    "regions": "https://outages.topenergy.co.nz/api/outages/regions",
    "kmzPlanned": "https://outages.topenergy.co.nz/storage/kmz/polygonsPlannedAll.kmz",
    "kmzActive": "https://outages.topenergy.co.nz/storage/kmz/polygonsActiveAll.kmz",
    "kmzAll": "https://outages.topenergy.co.nz/storage/kmz/polygonsAll.kmz",
    "mapUrl": "https://outages.topenergy.co.nz/"
  },
  "archiveBase": "topenergy/archive/2026-05-17/20260517_000125",
  "screenshot": {
    "attempted": false,
    "captured": false,
    "currentPath": "topenergy/current/mapScreenshot.png"
  },
  "outageInfo": {
    "enabled": true,
    "currentDir": "topenergy/current/outages",
    "archiveDir": "topenergy/archive/2026-05-17/20260517_000125/outages",
    "endpointTemplate": "https://outages.topenergy.co.nz/api/outage/{id}/info",
    "totalIds": 14,
    "failedIds": []
  },
  "files": [
    {
      "key": "outages",
      "currentPath": "topenergy/current/outages.json",
      "sha256": "474c61e28afb86b2e89bd2640bab58107244275beb44fa84bb4a9d8c6af627b0",
      "sourceUrl": "https://outages.topenergy.co.nz/api/outages",
      "byteLength": 1459
    },
    {
      "key": "regions",
      "currentPath": "topenergy/current/regions.json",
      "sha256": "900d8f8d950af040d12b36825750aab9bb5d167578aa2052e7b3f8f0dcb04645",
      "sourceUrl": "https://outages.topenergy.co.nz/api/outages/regions",
      "byteLength": 6012
    },
    {
      "key": "polygonsPlannedAll",
      "currentPath": "topenergy/current/polygonsPlannedAll.kmz",
      "sha256": "f6d20254503e7cacc96ca85f86c6375d08de8e61435aead0f2e86f94b0831fcd",
      "sourceUrl": "https://outages.topenergy.co.nz/storage/kmz/polygonsPlannedAll.kmz",
      "byteLength": 16551
    },
    {
      "key": "polygonsActiveAll",
      "currentPath": "topenergy/current/polygonsActiveAll.kmz",
      "sha256": "d92dae5f5986bdb7b890cd652b84ce36c7bdc4cb10ddb9e57c507f7b9d6d2d6b",
      "sourceUrl": "https://outages.topenergy.co.nz/storage/kmz/polygonsActiveAll.kmz",
      "byteLength": 351
    },
    {
      "key": "polygonsAll",
      "currentPath": "topenergy/current/polygonsAll.kmz",
      "sha256": "01510dcecf93bfe750de3869af13ff26190ec2be316eac07648549d44fa156e9",
      "sourceUrl": "https://outages.topenergy.co.nz/storage/kmz/polygonsAll.kmz",
      "byteLength": 16530
    }
  ]
}
