{
  "fetchedAt": "2026-05-18T12:00:25.246Z",
  "timezone": "Pacific/Auckland",
  "trigger": {
    "type": "outages",
    "previousSha256": "6d4fb7c38bcef0d460ca447cd67ce79c895c17180126898ef875f203e1bc4c1e",
    "newSha256": "ee942365a6b1aada18d8f567db53a41e4c3779a4ca6f5a749c55bdd30277551e"
  },
  "sources": {
    "outages": "https://outages.topenergy.co.nz/api/outages",
    "regions": "https://outages.topenergy.co.nz/api/outages/regions",
    "kmzPlanned": "https://outages.topenergy.co.nz/storage/kmz/polygonsPlannedAll.kmz",
    "kmzActive": "https://outages.topenergy.co.nz/storage/kmz/polygonsActiveAll.kmz",
    "kmzAll": "https://outages.topenergy.co.nz/storage/kmz/polygonsAll.kmz",
    "mapUrl": "https://outages.topenergy.co.nz/"
  },
  "archiveBase": "topenergy/archive/2026-05-19/20260519_000025",
  "screenshot": {
    "attempted": false,
    "captured": false,
    "currentPath": "topenergy/current/mapScreenshot.png"
  },
  "outageInfo": {
    "enabled": true,
    "currentDir": "topenergy/current/outages",
    "archiveDir": "topenergy/archive/2026-05-19/20260519_000025/outages",
    "endpointTemplate": "https://outages.topenergy.co.nz/api/outage/{id}/info",
    "totalIds": 17,
    "failedIds": []
  },
  "files": [
    {
      "key": "outages",
      "currentPath": "topenergy/current/outages.json",
      "sha256": "ee942365a6b1aada18d8f567db53a41e4c3779a4ca6f5a749c55bdd30277551e",
      "sourceUrl": "https://outages.topenergy.co.nz/api/outages",
      "byteLength": 1758
    },
    {
      "key": "regions",
      "currentPath": "topenergy/current/regions.json",
      "sha256": "69cc831852593a11751f546248d384674df738a3daf4d85a9f7cc029b42b90e9",
      "sourceUrl": "https://outages.topenergy.co.nz/api/outages/regions",
      "byteLength": 7284
    },
    {
      "key": "polygonsPlannedAll",
      "currentPath": "topenergy/current/polygonsPlannedAll.kmz",
      "sha256": "6157d5cabb340c4c0050ac5399d5608c88d91a542d5cefb8c7dbb10c946e0073",
      "sourceUrl": "https://outages.topenergy.co.nz/storage/kmz/polygonsPlannedAll.kmz",
      "byteLength": 20065
    },
    {
      "key": "polygonsActiveAll",
      "currentPath": "topenergy/current/polygonsActiveAll.kmz",
      "sha256": "b396caff54195be52b6a21f1d507a96d58416f93db8b9f4f15c303307483f045",
      "sourceUrl": "https://outages.topenergy.co.nz/storage/kmz/polygonsActiveAll.kmz",
      "byteLength": 351
    },
    {
      "key": "polygonsAll",
      "currentPath": "topenergy/current/polygonsAll.kmz",
      "sha256": "76c600d35700addefa279ca8e25ce0f376c667e438ab22963faae0d99604e116",
      "sourceUrl": "https://outages.topenergy.co.nz/storage/kmz/polygonsAll.kmz",
      "byteLength": 19997
    }
  ]
}
