{
  "fetchedAt": "2026-03-06T19:23:40.758Z",
  "timezone": "Pacific/Auckland",
  "trigger": {
    "type": "outages",
    "previousSha256": "038fb74bbb09ceaca85bfa043ae94ef881b8ce7a5672a464f9ae419948908917",
    "newSha256": "9609f4a92fe729f979a7548e0e0cfc3ea178655fe5dffec652e93139c0699d07"
  },
  "sources": {
    "outages": "https://outages.topenergy.co.nz/api/outages",
    "regions": "https://outages.topenergy.co.nz/api/outages/regions",
    "kmzPlanned": "https://outages.topenergy.co.nz/storage/kmz/polygonsPlannedAll.kmz",
    "kmzActive": "https://outages.topenergy.co.nz/storage/kmz/polygonsActiveAll.kmz",
    "kmzAll": "https://outages.topenergy.co.nz/storage/kmz/polygonsAll.kmz",
    "mapUrl": "https://outages.topenergy.co.nz/"
  },
  "archiveBase": "topenergy/archive/2026-03-07/20260307_082340",
  "screenshot": {
    "attempted": true,
    "captured": true,
    "currentPath": "topenergy/current/mapScreenshot.png"
  },
  "outageInfo": {
    "enabled": true,
    "currentDir": "topenergy/current/outages",
    "archiveDir": "topenergy/archive/2026-03-07/20260307_082340/outages",
    "endpointTemplate": "https://outages.topenergy.co.nz/api/outage/{id}/info",
    "totalIds": 15,
    "failedIds": []
  },
  "files": [
    {
      "key": "outages",
      "currentPath": "topenergy/current/outages.json",
      "sha256": "9609f4a92fe729f979a7548e0e0cfc3ea178655fe5dffec652e93139c0699d07",
      "sourceUrl": "https://outages.topenergy.co.nz/api/outages",
      "byteLength": 1556
    },
    {
      "key": "regions",
      "currentPath": "topenergy/current/regions.json",
      "sha256": "e357ea5398d7a51a58d260ce313d1c6107df07b56937b87838cd095a78b0923b",
      "sourceUrl": "https://outages.topenergy.co.nz/api/outages/regions",
      "byteLength": 6539
    },
    {
      "key": "polygonsPlannedAll",
      "currentPath": "topenergy/current/polygonsPlannedAll.kmz",
      "sha256": "1c8f85923ca89c2b5231f6011abab6a6db6988784912ccc49e90baa2928d672c",
      "sourceUrl": "https://outages.topenergy.co.nz/storage/kmz/polygonsPlannedAll.kmz",
      "byteLength": 16767
    },
    {
      "key": "polygonsActiveAll",
      "currentPath": "topenergy/current/polygonsActiveAll.kmz",
      "sha256": "31b8e061c3fa801b56d61a70097a2fc1ea3e0c44e0d76635c23eee4e7be47bf2",
      "sourceUrl": "https://outages.topenergy.co.nz/storage/kmz/polygonsActiveAll.kmz",
      "byteLength": 351
    },
    {
      "key": "polygonsAll",
      "currentPath": "topenergy/current/polygonsAll.kmz",
      "sha256": "e15b2cc773830ba4759c90572956d2695eb88914cadb607d8704a65361b5f2bb",
      "sourceUrl": "https://outages.topenergy.co.nz/storage/kmz/polygonsAll.kmz",
      "byteLength": 16730
    },
    {
      "key": "mapScreenshot",
      "currentPath": "topenergy/current/mapScreenshot.png",
      "sha256": "fa86b16e653a6b457abcb18757d9f6ea1df54568377b105705b0429588bedc35",
      "sourceUrl": "https://outages.topenergy.co.nz/",
      "byteLength": 398684
    }
  ]
}
