{
  "fetchedAt": "2026-03-10T20:55:40.423Z",
  "timezone": "Pacific/Auckland",
  "trigger": {
    "type": "outages",
    "previousSha256": "77076cd24fa85fbd989a62b08af76f069a1e9a9e1a945f8c56b2c9c862faf28d",
    "newSha256": "ea7a7c0e3c4bbd01f08b17e44164c6506c392ad164bc275db1c372d2eeeebb75"
  },
  "sources": {
    "outages": "https://outages.topenergy.co.nz/api/outages",
    "regions": "https://outages.topenergy.co.nz/api/outages/regions",
    "kmzPlanned": "https://outages.topenergy.co.nz/storage/kmz/polygonsPlannedAll.kmz",
    "kmzActive": "https://outages.topenergy.co.nz/storage/kmz/polygonsActiveAll.kmz",
    "kmzAll": "https://outages.topenergy.co.nz/storage/kmz/polygonsAll.kmz",
    "mapUrl": "https://outages.topenergy.co.nz/"
  },
  "archiveBase": "topenergy/archive/2026-03-11/20260311_095540",
  "screenshot": {
    "attempted": true,
    "captured": true,
    "currentPath": "topenergy/current/mapScreenshot.png"
  },
  "outageInfo": {
    "enabled": true,
    "currentDir": "topenergy/current/outages",
    "archiveDir": "topenergy/archive/2026-03-11/20260311_095540/outages",
    "endpointTemplate": "https://outages.topenergy.co.nz/api/outage/{id}/info",
    "totalIds": 18,
    "failedIds": []
  },
  "files": [
    {
      "key": "outages",
      "currentPath": "topenergy/current/outages.json",
      "sha256": "ea7a7c0e3c4bbd01f08b17e44164c6506c392ad164bc275db1c372d2eeeebb75",
      "sourceUrl": "https://outages.topenergy.co.nz/api/outages",
      "byteLength": 1852
    },
    {
      "key": "regions",
      "currentPath": "topenergy/current/regions.json",
      "sha256": "97544d15a61290566e19e5bc7cc9081b68603a87e1756b6be26135a1d9d02509",
      "sourceUrl": "https://outages.topenergy.co.nz/api/outages/regions",
      "byteLength": 7782
    },
    {
      "key": "polygonsPlannedAll",
      "currentPath": "topenergy/current/polygonsPlannedAll.kmz",
      "sha256": "a391abb128d84718085064894a44f7798e8aafa4698c4007145916065acff0f9",
      "sourceUrl": "https://outages.topenergy.co.nz/storage/kmz/polygonsPlannedAll.kmz",
      "byteLength": 19503
    },
    {
      "key": "polygonsActiveAll",
      "currentPath": "topenergy/current/polygonsActiveAll.kmz",
      "sha256": "5bc006b940739bcc6b9816f7d83d84687956fc2fbdc54e9a8757ae8bdf9e2a11",
      "sourceUrl": "https://outages.topenergy.co.nz/storage/kmz/polygonsActiveAll.kmz",
      "byteLength": 4182
    },
    {
      "key": "polygonsAll",
      "currentPath": "topenergy/current/polygonsAll.kmz",
      "sha256": "5ca177448394b63f98359e1b2eb68efdff49a8c9225b141567e38494fd3f71cb",
      "sourceUrl": "https://outages.topenergy.co.nz/storage/kmz/polygonsAll.kmz",
      "byteLength": 20738
    },
    {
      "key": "mapScreenshot",
      "currentPath": "topenergy/current/mapScreenshot.png",
      "sha256": "4bd64133cf8e18a788f87c8b08c7a356097d143f4a21070c941028c50eae7a5d",
      "sourceUrl": "https://outages.topenergy.co.nz/",
      "byteLength": 411314
    }
  ]
}
